gynx/__init__.py
gynx/app.py
gynx/settings.py
gynx/core/__init__.py
gynx/core/scheduler.py
gynx/credentials/credentials.json
gynx/files/__init__.py
gynx/files/changes.py
gynx/files/differences.py
gynx/files/operations.py
gynx/files/readers.py
gynx/files/events/__init__.py
gynx/files/events/handlers.py
gynx-0.0.8.data/scripts/gynx
gynx-0.0.8.data/scripts/gynx_run.py
gynx-0.0.8.dist-info/LICENSE.md
gynx-0.0.8.dist-info/METADATA
gynx-0.0.8.dist-info/WHEEL
gynx-0.0.8.dist-info/top_level.txt
gynx-0.0.8.dist-info/RECORD
