Metadata-Version: 2.1
Name: gynx
Version: 0.0.8
Summary: Google Drive sync client for Linux
Home-page: https://gitlab.com/ml394/gynx.git
Author: Matthew Levy
Author-email: matt@webkolektiv.com
License: GPL
Platform: UNKNOWN
Classifier: Development Status :: 2 - Pre-Alpha
Classifier: Environment :: Console
Classifier: Intended Audience :: End Users/Desktop
Classifier: License :: OSI Approved :: GNU Lesser General Public License v3 (LGPLv3)
Classifier: Natural Language :: English
Classifier: Operating System :: POSIX :: Linux
Classifier: Programming Language :: Python :: 3
Classifier: Topic :: System :: Archiving :: Backup
Classifier: Topic :: System :: Filesystems
Requires-Dist: dictdiffer (==0.7.1)
Requires-Dist: google-api-python-client (==1.7.11)
Requires-Dist: google-auth (==1.7.1)
Requires-Dist: google-auth-httplib2 (==0.0.3)
Requires-Dist: httplib2 (==0.14.0)
Requires-Dist: oauth2client (==4.1.3)
Requires-Dist: pyasn1 (==0.4.6)
Requires-Dist: pytz (==2018.7)
Requires-Dist: schedule (==0.6.0)
Requires-Dist: watchdog (==0.9.0)
